{"cameraMode":{"drawMode":0,"name":"Shaded","section":"Shading Mode"},"sceneLighting":true,"audioPlay":false,"sceneViewState":{"m_AlwaysRefresh":false,"showFog":true,"showSkybox":true,"showFlares":true,"showImageEffects":true,"showParticleSystems":true,"showVisualEffectGraphs":true,"m_FxEnabled":true},"in2DMode":false,"pivot":{"x":595.6365966796875,"y":249.8876953125,"z":-76.46479797363281},"rotation":{"x":0.10083600878715515,"y":0.2169971764087677,"z":-0.02250584214925766,"w":0.9707151055335999},"size":425.6304016113281,"orthographic":false}